confluence_calendar_api/__init__.py
confluence_calendar_api/confluence_calendar_api.py
confluence_calendar_api/decorators.py
confluence_calendar_api/exceptions.py
confluence_calendar_api/version.py
confluence_calendar_api-0.3.0.dist-info/LICENSE
confluence_calendar_api-0.3.0.dist-info/METADATA
confluence_calendar_api-0.3.0.dist-info/WHEEL
confluence_calendar_api-0.3.0.dist-info/top_level.txt
confluence_calendar_api-0.3.0.dist-info/RECORD
