Metadata-Version: 2.1
Name: confluence-calendar-api
Version: 0.3.0
Summary: Confluence Calendar API Python Wrapper
Home-page: https://github.com/Knuckles-Team/confluence-calendar-api
Author: Audel Rouhi
Author-email: knucklessg1@gmail.com
License: Unlicense
Platform: UNKNOWN
Classifier: Development Status :: 5 - Production/Stable
Classifier: License :: Public Domain
Classifier: Environment :: Console
Classifier: Operating System :: POSIX :: Linux
Classifier: Programming Language :: Python :: 3.8
Classifier: Programming Language :: Python :: 3.9
Classifier: Programming Language :: Python :: 3.10
Classifier: Programming Language :: Python :: 3.11
Classifier: Programming Language :: Python :: 3.12
License-File: LICENSE
Requires-Dist: requests (>=2.28.1)
Requires-Dist: urllib3 (>=1.26.13)
